src/__init__.py
src/myLogging.py
myColorfulLog-1.3.0.dist-info/METADATA
myColorfulLog-1.3.0.dist-info/WHEEL
myColorfulLog-1.3.0.dist-info/top_level.txt
myColorfulLog-1.3.0.dist-info/RECORD
